odoo8_addon_logging_json-8.0.1.0.0.99.dev4-py2.7-nspkg.pth
odoo8_addon_logging_json-8.0.1.0.0.99.dev4.dist-info/METADATA
odoo8_addon_logging_json-8.0.1.0.0.99.dev4.dist-info/RECORD
odoo8_addon_logging_json-8.0.1.0.0.99.dev4.dist-info/WHEEL
odoo8_addon_logging_json-8.0.1.0.0.99.dev4.dist-info/namespace_packages.txt
odoo8_addon_logging_json-8.0.1.0.0.99.dev4.dist-info/top_level.txt
odoo_addons/logging_json/README.rst
odoo_addons/logging_json/__init__.py
odoo_addons/logging_json/__openerp__.py
odoo_addons/logging_json/json_log.py
odoo_addons/logging_json/i18n/logging_json.pot
odoo_addons/logging_json/static/description/icon.png
